mcp_pypi_jhl_weather_server/__init__.py
mcp_pypi_jhl_weather_server-0.1.1.dist-info/METADATA
mcp_pypi_jhl_weather_server-0.1.1.dist-info/WHEEL
mcp_pypi_jhl_weather_server-0.1.1.dist-info/entry_points.txt
mcp_pypi_jhl_weather_server-0.1.1.dist-info/RECORD
