Metadata-Version: 2.4
Name: mcp-pypi-jhl-weather-server
Version: 0.1.1
Summary: 这是一个测试上传到pypi的mcp服务器demo。
Author-email: jhl <2310916034@qq.com>
Requires-Python: >=3.12
